src/__init__.py
src/quizium_prompt/__init__.py
src/quizium_prompt/transcript_processor.py
quizium_prompt-0.0.2.dist-info/METADATA
quizium_prompt-0.0.2.dist-info/WHEEL
quizium_prompt-0.0.2.dist-info/top_level.txt
quizium_prompt-0.0.2.dist-info/RECORD
