Metadata-Version: 2.1
Name: quizium-prompt
Version: 0.0.2
Summary: Chapter, MCQ prompts
Home-page: https://github.com/riiid/quizium-prompt
Author: dongwon.kim
Author-email: dongwon.kim@riiid.co
License: MIT
Keywords: quizium,prompt
Classifier: Programming Language :: Python :: 3
Classifier: License :: OSI Approved :: MIT License
Classifier: Operating System :: OS Independent
Requires-Python: >=3.11.3
Requires-Dist: openai >=1.2.3
Requires-Dist: spacy >=3.7.2
